lcsscaseapi/__init__.py
lcsscaseapi/client.py
lcsscaseapi/constants.py
lcsscaseapi/types.py
lcsscaseapi-0.0.6.dist-info/LICENSE
lcsscaseapi-0.0.6.dist-info/METADATA
lcsscaseapi-0.0.6.dist-info/WHEEL
lcsscaseapi-0.0.6.dist-info/top_level.txt
lcsscaseapi-0.0.6.dist-info/RECORD
