Metadata-Version: 2.1
Name: lcsscaseapi
Version: 0.0.6
Summary: A package to easily download and manipulate the lcss case datasets
Home-page: https://github.com/SKAshwin/caseapi-wrapper
Author: Sanil Kumar Ashwin
Author-email: sanil.kumar.ashwin@gmail.com
License: UNKNOWN
Project-URL: Bug Tracker, https://github.com/SKAshwin/caseapi-wrapper/issues
Platform: UNKNOWN
Classifier: Programming Language :: Python :: 3
Classifier: License :: OSI Approved :: MIT License
Classifier: Operating System :: OS Independent
Requires-Python: >=3.6
License-File: LICENSE
Requires-Dist: requests (==2.26.0)
Requires-Dist: Django (==3.2.7)
